eventiq_fastapi/__about__.py
eventiq_fastapi/__init__.py
eventiq_fastapi/asyncapi.py
eventiq_fastapi/dependencies.py
eventiq_fastapi/healthcheck.py
eventiq_fastapi/lifespan.py
eventiq_fastapi/py.typed
eventiq_fastapi-0.1.0.dist-info/METADATA
eventiq_fastapi-0.1.0.dist-info/WHEEL
eventiq_fastapi-0.1.0.dist-info/licenses/LICENSE
eventiq_fastapi-0.1.0.dist-info/RECORD
